eulith_web3/__init__.py
eulith_web3/ace.py
eulith_web3/atomic.py
eulith_web3/common.py
eulith_web3/curve.py
eulith_web3/eip712_types.py
eulith_web3/erc20.py
eulith_web3/eulith_service.py
eulith_web3/eulith_web3.py
eulith_web3/exceptions.py
eulith_web3/fireblocks.py
eulith_web3/kms.py
eulith_web3/ledger.py
eulith_web3/lightsim.py
eulith_web3/pendle.py
eulith_web3/requests.py
eulith_web3/response.py
eulith_web3/signer.py
eulith_web3/signing.py
eulith_web3/swap.py
eulith_web3/trezor.py
eulith_web3/uniswap.py
eulith_web3/websocket.py
eulith_web3/whitelists.py
eulith_web3/contract_bindings/__init__.py
eulith_web3/contract_bindings/i_e_r_c20.py
eulith_web3/contract_bindings/i_e_r_c_detailed.py
eulith_web3/contract_bindings/i_uniswap_v3_pool.py
eulith_web3/contract_bindings/w_e_t_h_interface.py
eulith_web3/contract_bindings/convex/__init__.py
eulith_web3/contract_bindings/convex/i_booster.py
eulith_web3/contract_bindings/convex/i_convex_deposits.py
eulith_web3/contract_bindings/convex/i_reward_staking.py
eulith_web3/contract_bindings/convex/i_rewards.py
eulith_web3/contract_bindings/curve/__init__.py
eulith_web3/contract_bindings/curve/curve_v2_eth_crv.py
eulith_web3/contract_bindings/curve/curve_v2_eth_crv_gauge.py
eulith_web3/contract_bindings/curve/curve_v2_eth_ldo.py
eulith_web3/contract_bindings/curve/curve_v2_eth_ldo_gauge.py
eulith_web3/contract_bindings/curve/curve_v2_eth_matic.py
eulith_web3/contract_bindings/curve/curve_v2_eth_matic_gauge.py
eulith_web3/contract_bindings/curve/curve_v2_three_pool.py
eulith_web3/contract_bindings/curve/curve_v2_tri_crypto.py
eulith_web3/contract_bindings/gmx/__init__.py
eulith_web3/contract_bindings/gmx/i_glp_manager.py
eulith_web3/contract_bindings/gmx/i_order_book.py
eulith_web3/contract_bindings/gmx/i_position_router.py
eulith_web3/contract_bindings/gmx/i_reader.py
eulith_web3/contract_bindings/gmx/i_reward_router.py
eulith_web3/contract_bindings/gmx/i_reward_tracker.py
eulith_web3/contract_bindings/gmx/i_router.py
eulith_web3-0.27.0.dist-info/LICENSE
eulith_web3-0.27.0.dist-info/METADATA
eulith_web3-0.27.0.dist-info/WHEEL
eulith_web3-0.27.0.dist-info/top_level.txt
eulith_web3-0.27.0.dist-info/RECORD
