Metadata-Version: 2.1
Name: eulith_web3
Version: 0.27.0
Summary: A Web3.py compatible wrapper library for Eulith clients
Author-email: Eulith Team <kristian@eulith.com>
Classifier: Programming Language :: Python :: 3
Classifier: License :: OSI Approved :: MIT License
Classifier: Operating System :: OS Independent
Requires-Python: >=3.8
License-File: LICENSE
Requires-Dist: web3 <7.0,>=5.31.1
Requires-Dist: boto3
Requires-Dist: asn1
Requires-Dist: uuid
Requires-Dist: requests
Requires-Dist: hexbytes
Requires-Dist: cytoolz
Requires-Dist: botocore
Requires-Dist: fireblocks-sdk
Requires-Dist: websocket-client
Requires-Dist: ledgerblue
Requires-Dist: trezor
